encontrar/__init__.py
encontrar/locate.py
encontrar-1.1.0.dist-info/METADATA
encontrar-1.1.0.dist-info/WHEEL
encontrar-1.1.0.dist-info/top_level.txt
encontrar-1.1.0.dist-info/RECORD
