Metadata-Version: 2.1
Name: encontrar
Version: 1.1.0
Summary: Locate the path you're in and append it to sys
Author: tmorales (Tomas Morales Vera)
Author-email: <moralesveratomas@gmail.com>
Keywords: python,path,locate,locator,pathLocator,pathLocate
Classifier: Development Status :: 1 - Planning
Classifier: Programming Language :: Python :: 3.10
